glass/ext/camb.py
glass.ext.camb-2023.6.dist-info/METADATA
glass.ext.camb-2023.6.dist-info/WHEEL
glass.ext.camb-2023.6.dist-info/licenses/LICENSE
glass.ext.camb-2023.6.dist-info/RECORD
