Metadata-Version: 2.1
Name: glass.ext.camb
Version: 2023.6
Summary: GLASS extension for CAMB
Project-URL: Homepage, https://github.com/glass-dev/glass.ext.camb
Project-URL: Issues, https://github.com/glass-dev/glass.ext.camb/issues
Maintainer-email: Nicolas Tessore <n.tessore@ucl.ac.uk>
License: MIT License
License-File: LICENSE
Classifier: License :: OSI Approved :: MIT License
Classifier: Operating System :: OS Independent
Classifier: Programming Language :: Python :: 3
Requires-Python: >=3.6
Requires-Dist: camb>=1.3.5
Requires-Dist: glass>=2023.6.dev0
Requires-Dist: numpy
Provides-Extra: test
Requires-Dist: pytest; extra == 'test'
